MANIFEST.in
README.md
setup.py
harrison/__init__.py
harrison/profile.py
harrison/registered_timer.py
harrison/test_timer.py
harrison/timer.py
harrison/util/__init__.py
harrison/util/inspectlib.py
harrison/util/test_inspectlib.py
metaboharrison.egg-info/PKG-INFO
metaboharrison.egg-info/SOURCES.txt
metaboharrison.egg-info/dependency_links.txt
metaboharrison.egg-info/top_level.txt