Metadata-Version: 2.1
Name: metaboharrison
Version: 1.2.0
Summary: Time a block of code
Home-page: https://github.com/metabolize/harrison
Author: Body Labs
Author-email: david.smith@bodylabs.com, paul.melnikow@bodylabs.com
License: MIT
Platform: UNKNOWN
Classifier: Development Status :: 3 - Alpha
Classifier: Intended Audience :: Developers
Classifier: License :: OSI Approved :: BSD License
Classifier: Operating System :: OS Independent
Classifier: Programming Language :: Python :: 2.7
Classifier: Programming Language :: Python :: 3
